{
  "狸猫之道": "盗宝狸猫娘",
  "断章伪典": "死亡伪典",
  "石化之瞳": "美杜莎",
  "暖暖缎带": "暖暖",
  "发卡播放器": "哔哩哔哩·33娘",
  "希望苏生程序": "七海千秋",
  "黑白熊AI Core": "黑白熊",
  "miHoYo超级手机": "崩坏娘",
  "灵依娘的本体": "灵依娘",
  "特技厨师之证": "普蕾提",
  "女仆特制巧克力（无毒）": "昴星团战斗女仆",
  "熊印软糖": "茵朵兰",
  "幻想构造": "休伯利安",
  "荣誉碎片": "Kar98k",
  "樱桃与泪石": "柯罗伊",
  "负罪之羽": "夜天少女",
  "喰时之卵": "暗时计",
  "绯炎绘马": "绯狱丸",
  "雨之石": "雨",
  "八齿红玉": "尤莉娅",
  "兔耳金平糖": "书包酱",
  "紫苑风瞳": "红",
  "幽光鞘翅": "耀夜姬",
  "量子核心": "重装小兔",
  "星象轮盘": "科斯的无名之女",
  "水银子弹": "克劳迪娅",
  "真夏冰晶": "冰铃",
  "遗迹之心": "法拉之翼",
  "夕雾之约": "巴利尔·慕恋",
  "憧憬之羽": "夜天少女·憧憬",
  "太阳骑士的吊坠": "阿拉迪雅",
  "薛定谔铃铛": "量子小猫",
  "自转齿轮": "壳之幼子",
  "骑士烙印": "琉璃",
  "深海欠片": "童话世界的席丽雅",
  "Hana": "萌",
  "杀生血玉": "八重樱",
  "恪心碎甲": "赫尔薇尔",
  "魔神结晶": "巴利尔",
  "猫眼魔药": "杰伦塔尼娅",
  "芙蕾雅之梦": "芙蕾雅",
  "罪之石": "普洛姆特",
  "V制式核心": "V制式·Core融合",
  "陨星之尘": "奥菲丽娅",
  "永夜之石": "暗时计·永夜",
  "蝠翼南瓜糖": "书包酱·万圣",
  "圣诞花环": "芙蕾雅·Xmas",
  "虹之嵌片": "德哈琳",
  "破产基金": "卡奈",
  "剧毒皇冠": "毒药",
  "吼姆钥匙扣": "吼姆",
  "救世主异闻录": "斯库丽特",
  "星彩音符": "绮罗",
  "毛茸茸幼崽": "毛茸茸结社",
  "心之钥": "莉兹",
  "天魔之翼": "芙兰",
  "构造之灵": "康娜霍德",
  "深海化石": "幽",
  "胡萝卜发卡": "艾薇娅",
  "发条小鸟": "片翼",
  "部落图腾": "萨拉",
  "罪之匙": "普洛姆特·午夜狂欢",
  "月光晶片": "月光王座",
  "精密运算器": "爱酱",
  "焚火之源": "精卫",
  "兔叽变身器": "书包酱·魔法少女",
  "雪色发饰": "冰铃·绝对零度",
  "枫色发卡": "红枫刺客",
  "机装启动器": "无限追击"
}
